anemoi/inference/__init__.py
anemoi/inference/__main__.py
anemoi/inference/_version.py
anemoi/inference/checkpoint.py
anemoi/inference/checks.py
anemoi/inference/context.py
anemoi/inference/decorators.py
anemoi/inference/device.py
anemoi/inference/forcings.py
anemoi/inference/input.py
anemoi/inference/lazy.py
anemoi/inference/legacy.py
anemoi/inference/metadata.py
anemoi/inference/output.py
anemoi/inference/patch.py
anemoi/inference/plugin.py
anemoi/inference/precisions.py
anemoi/inference/processor.py
anemoi/inference/profiler.py
anemoi/inference/protocol.py
anemoi/inference/provenance.py
anemoi/inference/runner.py
anemoi/inference/state.py
anemoi/inference/task.py
anemoi/inference/trace.py
anemoi/inference/transport.py
anemoi/inference/types.py
anemoi/inference/variables.py
anemoi/inference/commands/__init__.py
anemoi/inference/commands/couple.py
anemoi/inference/commands/inspect.py
anemoi/inference/commands/metadata.py
anemoi/inference/commands/patch.py
anemoi/inference/commands/requests.py
anemoi/inference/commands/retrieve.py
anemoi/inference/commands/run.py
anemoi/inference/commands/sanitise.py
anemoi/inference/commands/validate.py
anemoi/inference/config/__init__.py
anemoi/inference/config/couple.py
anemoi/inference/config/run.py
anemoi/inference/grib/__init__.py
anemoi/inference/grib/encoding.py
anemoi/inference/grib/templates/__init__.py
anemoi/inference/grib/templates/builtin.py
anemoi/inference/grib/templates/builtin.yaml
anemoi/inference/grib/templates/file.py
anemoi/inference/grib/templates/manager.py
anemoi/inference/grib/templates/samples.py
anemoi/inference/inputs/__init__.py
anemoi/inference/inputs/cds.py
anemoi/inference/inputs/cutout.py
anemoi/inference/inputs/dataset.py
anemoi/inference/inputs/dummy.py
anemoi/inference/inputs/ekd.py
anemoi/inference/inputs/empty.py
anemoi/inference/inputs/fdb.py
anemoi/inference/inputs/grib.py
anemoi/inference/inputs/gribfile.py
anemoi/inference/inputs/icon.py
anemoi/inference/inputs/mars.py
anemoi_inference-0.8.1.dist-info/licenses/LICENSE
anemoi_inference-0.8.1.dist-info/METADATA
anemoi_inference-0.8.1.dist-info/WHEEL
anemoi_inference-0.8.1.dist-info/entry_points.txt
anemoi_inference-0.8.1.dist-info/top_level.txt
anemoi_inference-0.8.1.dist-info/RECORD
