Metadata-Version: 2.4
Name: anemoi-inference
Version: 0.8.1
Summary: A package to run inference from data-driven forecasts weather models.
Author-email: "European Centre for Medium-Range Weather Forecasts (ECMWF)" <software.support@ecmwf.int>
License:                                  Apache License
Project-URL: Documentation, https://anemoi-inference.readthedocs.io/
Project-URL: Homepage, https://github.com/ecmwf/anemoi-inference/
Project-URL: Issues, https://github.com/ecmwf/anemoi-inference/issues
Project-URL: Repository, https://github.com/ecmwf/anemoi-inference/
Keywords: ai,inference,tools
Classifier: Development Status :: 4 - Beta
Classifier: Intended Audience :: Developers
Classifier: License :: OSI Approved :: Apache Software License
Classifier: Operating System :: OS Independent
Classifier: Programming Language :: Python :: 3 :: Only
Classifier: Programming Language :: Python :: 3.10
Classifier: Programming Language :: Python :: 3.11
Classifier: Programming Language :: Python :: 3.12
Classifier: Programming Language :: Python :: 3.13
Classifier: Programming Language :: Python :: Implementation :: CPython
Classifier: Programming Language :: Python :: Implementation :: PyPy
Requires-Python: >=3.10
License-File: LICENSE
Requires-Dist: anemoi-transform>0.1.13
Requires-Dist: anemoi-utils[provenance,text]>=0.4.32
Requires-Dist: aniso8601
Requires-Dist: anytree
Requires-Dist: deprecation
Requires-Dist: earthkit-data>=0.12.4
Requires-Dist: eccodes>=2.38.3
Requires-Dist: numpy
Requires-Dist: omegaconf<2.4,>=2.2
Requires-Dist: packaging
Requires-Dist: pydantic
Requires-Dist: pyyaml
Requires-Dist: semantic-version
Requires-Dist: torch
Provides-Extra: all
Requires-Dist: anemoi-datasets; extra == "all"
Requires-Dist: anemoi-inference[huggingface,plot,tests,zarr]; extra == "all"
Requires-Dist: anemoi-utils[all]>=0.4.32; extra == "all"
Provides-Extra: cosmo
Requires-Dist: eccodes<=2.39.1; extra == "cosmo"
Requires-Dist: eccodes-cosmo-resources-python; extra == "cosmo"
Provides-Extra: dev
Requires-Dist: anemoi-inference[all,docs,plugin,tests]; extra == "dev"
Provides-Extra: docs
Requires-Dist: autodoc-pydantic; extra == "docs"
Requires-Dist: nbsphinx; extra == "docs"
Requires-Dist: pandoc; extra == "docs"
Requires-Dist: rstfmt; extra == "docs"
Requires-Dist: sphinx<8.2; extra == "docs"
Requires-Dist: sphinx-argparse<0.5; extra == "docs"
Requires-Dist: sphinx-rtd-theme; extra == "docs"
Provides-Extra: huggingface
Requires-Dist: huggingface-hub; extra == "huggingface"
Provides-Extra: plot
Requires-Dist: earthkit-plots; extra == "plot"
Provides-Extra: plugin
Requires-Dist: ai-models>=0.7; extra == "plugin"
Requires-Dist: tqdm; extra == "plugin"
Provides-Extra: tests
Requires-Dist: anemoi-datasets[all]; extra == "tests"
Requires-Dist: anemoi-inference[all]; extra == "tests"
Requires-Dist: hypothesis; extra == "tests"
Requires-Dist: pytest; extra == "tests"
Requires-Dist: pytest-mock; extra == "tests"
Provides-Extra: zarr
Requires-Dist: zarr; extra == "zarr"
Dynamic: license-file
